treadi/__init__.py
treadi/auth.py
treadi/config.py
treadi/data.py
treadi/filter.lark
treadi/filter.py
treadi/issue_cache.py
treadi/issue_loader.py
treadi/main.py
treadi/repo_loader.py
treadi/repository_list.lark
treadi/ros_pmc_repos.txt
treadi/schema.docs.graphql
treadi/treadi.kv
treadi/treadi_icon.png
treadi/repository_lists.d/25_Public_repos_I_own.txt
treadi/repository_lists.d/90_OSRA_Gazebo_PMC.txt
treadi/repository_lists.d/90_OSRA_Infrastructure.txt
treadi/repository_lists.d/90_OSRA_Open-RMF_PMC.txt
treadi/repository_lists.d/90_OSRA_ROS_PMC.txt
treadi/repository_lists.d/90_OSRA_ros-controls_PMC.txt
treadi/repository_lists.d/README.md
treadi/screens/__init__.py
treadi/screens/issue_loading_screen.py
treadi/screens/issue_screen.py
treadi/screens/login_screen.py
treadi/screens/repo_loading_screen.py
treadi/screens/repo_picker_screen.py
treadi-0.10.0.dist-info/METADATA
treadi-0.10.0.dist-info/WHEEL
treadi-0.10.0.dist-info/entry_points.txt
treadi-0.10.0.dist-info/licenses/LICENSE
treadi-0.10.0.dist-info/RECORD
