Metadata-Version: 2.4
Name: TreadI
Version: 0.10.0
Summary: Add your description here
Project-URL: Homepage, https://sloretz.github.io/TreadI/
Project-URL: Source, https://github.com/sloretz/TreadI
Author-email: Shane Loretz <shane.loretz@gmail.com>
Maintainer-email: Shane Loretz <shane.loretz@gmail.com>
License-Expression: Apache-2.0
License-File: LICENSE
Classifier: Development Status :: 3 - Alpha
Classifier: Intended Audience :: Developers
Classifier: License :: OSI Approved :: Apache Software License
Classifier: Natural Language :: English
Classifier: Topic :: Software Development :: Bug Tracking
Classifier: Topic :: Utilities
Requires-Python: >=3.10
Requires-Dist: gql[requests]>=3.5.0
Requires-Dist: keyring>=25.6.0
Requires-Dist: kivy>=2.3.1
Requires-Dist: lark>=1.2.2
Requires-Dist: platformdirs>=4.3.6
Requires-Dist: python-dateutil>=2.8.0
Requires-Dist: pyyaml>=6.0.2
Requires-Dist: requests>=2.32.3
